generate_config/__init__.py
generate_config/generate.py
seagull2_generate_config_template-0.0.3.dist-info/LICENSE
seagull2_generate_config_template-0.0.3.dist-info/METADATA
seagull2_generate_config_template-0.0.3.dist-info/WHEEL
seagull2_generate_config_template-0.0.3.dist-info/top_level.txt
seagull2_generate_config_template-0.0.3.dist-info/RECORD
