Metadata-Version: 2.1
Name: seagull2-generate-config-template
Version: 0.0.3
Author: v-yangchao
Author-email: v-yangchao@sinooceangroup.com
License: Apache
Classifier: License :: OSI Approved :: Apache Software License
Classifier: Natural Language :: English
Classifier: Operating System :: OS Independent
Classifier: Programming Language :: Python
Classifier: Programming Language :: Python :: 3.10
Classifier: Topic :: Software Development :: Libraries :: Python Modules
Requires-Python: >=3.6
License-File: LICENSE
Requires-Dist: requests (>=2.26.0)
Requires-Dist: tenacity (>=8.2.1)
